agentry/__init__.py
agentry-0.0.1.dist-info/METADATA
agentry-0.0.1.dist-info/WHEEL
agentry-0.0.1.dist-info/licenses/LICENSE
agentry-0.0.1.dist-info/RECORD
