Metadata-Version: 2.4
Name: agentry
Version: 0.0.1
Summary: A library for creating AI agents
Project-URL: Homepage, https://github.com/penlight-ai/agentry
Author: Zaid Imad
License:                                  Apache License
License-File: LICENSE
Classifier: License :: OSI Approved :: Apache Software License
Classifier: Operating System :: OS Independent
Classifier: Programming Language :: Python :: 3
Classifier: Programming Language :: Python :: 3.11
Requires-Python: >=3.11
